pas/__init__.py
pas/plugins/__init__.py
pas/plugins/oidc/__init__.py
pas/plugins/oidc/configure.zcml
pas/plugins/oidc/interfaces.py
pas/plugins/oidc/plugins.py
pas/plugins/oidc/session.py
pas/plugins/oidc/setuphandlers.py
pas/plugins/oidc/testing.py
pas/plugins/oidc/utils.py
pas/plugins/oidc/browser/__init__.py
pas/plugins/oidc/browser/configure.zcml
pas/plugins/oidc/browser/view.py
pas/plugins/oidc/controlpanel/__init__.py
pas/plugins/oidc/controlpanel/classic.py
pas/plugins/oidc/controlpanel/configure.zcml
pas/plugins/oidc/controlpanel/deserializer.py
pas/plugins/oidc/controlpanel/oidc.py
pas/plugins/oidc/controlpanel/serializer.py
pas/plugins/oidc/locales/__init__.py
pas/plugins/oidc/locales/__main__.py
pas/plugins/oidc/locales/pas.plugins.oidc.pot
pas/plugins/oidc/locales/de/LC_MESSAGES/pas.plugins.oidc.po
pas/plugins/oidc/locales/en/LC_MESSAGES/pas.plugins.oidc.po
pas/plugins/oidc/locales/es/LC_MESSAGES/pas.plugins.oidc.po
pas/plugins/oidc/profiles/default/browserlayer.xml
pas/plugins/oidc/profiles/default/controlpanel.xml
pas/plugins/oidc/profiles/default/metadata.xml
pas/plugins/oidc/profiles/uninstall/browserlayer.xml
pas/plugins/oidc/services/__init__.py
pas/plugins/oidc/services/configure.zcml
pas/plugins/oidc/services/login/__init__.py
pas/plugins/oidc/services/login/configure.zcml
pas/plugins/oidc/services/login/get.py
pas/plugins/oidc/services/oidc/__init__.py
pas/plugins/oidc/services/oidc/configure.zcml
pas/plugins/oidc/services/oidc/oidc.py
pas/plugins/oidc/upgrades/__init__.py
pas/plugins/oidc/upgrades/configure.zcml
pas/plugins/oidc/www/oidcPluginForm.zpt
pas_plugins_oidc-2.0.0.dist-info/METADATA
pas_plugins_oidc-2.0.0.dist-info/WHEEL
pas_plugins_oidc-2.0.0.dist-info/entry_points.txt
pas_plugins_oidc-2.0.0.dist-info/licenses/LICENSE.GPL
pas_plugins_oidc-2.0.0.dist-info/licenses/LICENSE.md
pas_plugins_oidc-2.0.0.dist-info/RECORD
