Metadata-Version: 2.4
Name: pas.plugins.oidc
Version: 2.0.0
Summary: OIDC support for Plone sites
Project-URL: Homepage, https://github.com/collective/pas.plugins.oidc
Project-URL: PyPI, https://pypi.org/project/pas.plugins.oidc
Project-URL: Source, https://github.com/collective/pas.plugins.oidc
Project-URL: Tracker, https://github.com/collective/pas.plugins.oidc/issues
Author-email: Mauro Amico <mauro.amico@gmail.com>, Érico Andrei <ericof@plone.org>
License-Expression: GPL-2.0-only
License-File: LICENSE.GPL
License-File: LICENSE.md
Keywords: Authentication,CMS,OAuth,OIDC,PAS,Plone,Python
Classifier: Development Status :: 4 - Beta
Classifier: Environment :: Web Environment
Classifier: Framework :: Plone
Classifier: Framework :: Plone :: 6.0
Classifier: Framework :: Plone :: 6.1
Classifier: Framework :: Plone :: Addon
Classifier: License :: OSI Approved :: GNU General Public License v2 (GPLv2)
Classifier: Operating System :: OS Independent
Classifier: Programming Language :: Python
Classifier: Programming Language :: Python :: 3.10
Classifier: Programming Language :: Python :: 3.11
Classifier: Programming Language :: Python :: 3.12
Classifier: Programming Language :: Python :: 3.13
Requires-Python: >=3.10
Requires-Dist: oic
Requires-Dist: plone-api
Requires-Dist: plone-app-registry
Requires-Dist: plone-base
Requires-Dist: plone-protect
Requires-Dist: plone-restapi>=9.10.0
Requires-Dist: products-cmfcore
Requires-Dist: products-cmfplone>=6.0
Requires-Dist: requests
Requires-Dist: z3c-form
Requires-Dist: zope
Provides-Extra: test
Requires-Dist: plone-app-contenttypes; extra == 'test'
Requires-Dist: plone-app-testing; extra == 'test'
Requires-Dist: plone-restapi[test]; extra == 'test'
Requires-Dist: plone-testing; extra == 'test'
Requires-Dist: pytest; extra == 'test'
Requires-Dist: pytest-cov; extra == 'test'
Requires-Dist: pytest-docker; extra == 'test'
Requires-Dist: pytest-mock; extra == 'test'
Requires-Dist: pytest-plone>=0.5.0; extra == 'test'
Requires-Dist: requests-mock; extra == 'test'
Requires-Dist: zest-releaser[recommended]>=9.5.0; extra == 'test'
Requires-Dist: zestreleaser-towncrier>=1.3.0; extra == 'test'
